build/lib/systemdlint/__init__.py
build/lib/systemdlint/__main__.py
build/lib/systemdlint/cls/__init__.py
build/lib/systemdlint/cls/error.py
build/lib/systemdlint/cls/helper.py
build/lib/systemdlint/cls/limitation.py
build/lib/systemdlint/cls/parser.py
build/lib/systemdlint/cls/runargs.py
build/lib/systemdlint/cls/setting.py
build/lib/systemdlint/cls/specials.py
build/lib/systemdlint/cls/test.py
build/lib/systemdlint/cls/unititem.py
build/lib/systemdlint/cls/unittype.py
build/lib/systemdlint/cls/value.py
build/lib/systemdlint/conf/__init__.py
build/lib/systemdlint/conf/getTests.py
build/lib/systemdlint/conf/knownMandatory.py
build/lib/systemdlint/conf/knownPaths.py
build/lib/systemdlint/conf/knownSettings.py
build/lib/systemdlint/conf/knownUnits.py
systemdlint/__init__.py
systemdlint/__main__.py
systemdlint/cls/__init__.py
systemdlint/cls/error.py
systemdlint/cls/helper.py
systemdlint/cls/limitation.py
systemdlint/cls/parser.py
systemdlint/cls/runargs.py
systemdlint/cls/setting.py
systemdlint/cls/specials.py
systemdlint/cls/test.py
systemdlint/cls/unititem.py
systemdlint/cls/unittype.py
systemdlint/cls/value.py
systemdlint/conf/__init__.py
systemdlint/conf/getTests.py
systemdlint/conf/knownMandatory.py
systemdlint/conf/knownPaths.py
systemdlint/conf/knownSettings.py
systemdlint/conf/knownUnits.py
systemdlint-1.4.0.dist-info/licenses/LICENSE
systemdlint-1.4.0.dist-info/METADATA
systemdlint-1.4.0.dist-info/WHEEL
systemdlint-1.4.0.dist-info/entry_points.txt
systemdlint-1.4.0.dist-info/top_level.txt
systemdlint-1.4.0.dist-info/RECORD
