Metadata-Version: 2.4
Name: systemdlint
Version: 1.4.0
Summary: Systemd Unitfile Linter
Maintainer-email: Konrad Weihmann <kweihmann@outlook.com>
License-Expression: BSD-2-Clause
Project-URL: homepage, https://github.com/priv-kweihmann/systemdlint
Project-URL: repository, https://github.com/priv-kweihmann/systemdlint.git
Project-URL: bugtracker, https://github.com/priv-kweihmann/systemdlint/issues
Classifier: Development Status :: 4 - Beta
Classifier: Environment :: Console
Classifier: Intended Audience :: Developers
Classifier: Natural Language :: English
Classifier: Operating System :: POSIX :: Linux
Classifier: Programming Language :: Python :: 3 :: Only
Classifier: Programming Language :: Python :: 3
Classifier: Programming Language :: Python :: 3.10
Classifier: Programming Language :: Python :: 3.11
Classifier: Programming Language :: Python :: 3.12
Classifier: Programming Language :: Python :: 3.13
Classifier: Programming Language :: Python :: 3.9
Classifier: Topic :: Software Development :: Quality Assurance
Requires-Python: >=3.9
License-File: LICENSE
Requires-Dist: systemdunitparser>=0.4
Requires-Dist: anytree~=2.13
Provides-Extra: dev
Requires-Dist: Flake8-pyproject==1.2.3; extra == "dev"
Requires-Dist: build==1.3.0; extra == "dev"
Requires-Dist: flake8==7.3.0; extra == "dev"
Requires-Dist: twine==6.2.0; extra == "dev"
Requires-Dist: wheel~=0.45; extra == "dev"
Dynamic: license-file
